revpbuf/__init__.py
revpbuf/core.py
revpbuf/parser.py
revpbuf-0.1.1.dist-info/LICENSE.md
revpbuf-0.1.1.dist-info/METADATA
revpbuf-0.1.1.dist-info/WHEEL
revpbuf-0.1.1.dist-info/top_level.txt
revpbuf-0.1.1.dist-info/RECORD
