Metadata-Version: 2.1
Name: revpbuf
Version: 0.1.1
Summary: Reverse packed Google Protobuf payload.
Home-page: https://github.com/vpetrigo/rev-protobuf
Author: Vladimir Petrigo
Author-email: vladimir.petrigo@gmail.com
License: LICENSE.md
Platform: UNKNOWN
Classifier: License :: OSI Approved :: MIT License
Classifier: Programming Language :: Python
Classifier: Programming Language :: Python :: 3
Classifier: Programming Language :: Python :: 3.8
Classifier: Programming Language :: Python :: Implementation :: CPython
Classifier: Programming Language :: Python :: Implementation :: PyPy
Requires-Python: >=3.8.0
